docs/Makefile
docs/make.bat
docs/source/conf.py
docs/source/functions.rst
docs/source/index.rst
docs/source/installation.rst
vim_eof_comment/__init__.py
vim_eof_comment/__init__.pyi
vim_eof_comment/__main__.py
vim_eof_comment/eof.py
vim_eof_comment/eof.pyi
vim_eof_comment/file.py
vim_eof_comment/file.pyi
vim_eof_comment/py.typed
vim_eof_comment/regex.py
vim_eof_comment/regex.pyi
vim_eof_comment/types.py
vim_eof_comment/types.pyi
vim_eof_comment/util.py
vim_eof_comment/util.pyi
vim_eof_comment/version.py
vim_eof_comment/version.pyi
vim_eof_comment/args/__init__.py
vim_eof_comment/args/__init__.pyi
vim_eof_comment/args/completion.py
vim_eof_comment/args/completion.pyi
vim_eof_comment/args/parsing.py
vim_eof_comment/args/parsing.pyi
vim_eof_comment/comments/__init__.py
vim_eof_comment/comments/__init__.pyi
vim_eof_comment/comments/filetypes.json
vim_eof_comment/comments/generator.py
vim_eof_comment/comments/generator.pyi
vim_eof_comment-0.5.1.dist-info/licenses/LICENSE
vim_eof_comment-0.5.1.dist-info/METADATA
vim_eof_comment-0.5.1.dist-info/WHEEL
vim_eof_comment-0.5.1.dist-info/entry_points.txt
vim_eof_comment-0.5.1.dist-info/top_level.txt
vim_eof_comment-0.5.1.dist-info/RECORD
