Metadata-Version: 2.4
Name: vim-eof-comment
Version: 0.5.1
Summary: Adds Vim EOF modeline comments for given filetypes in given directories
Author-email: Guennadi Maximov C <g.maxc.fox@protonmail.com>
Maintainer-email: Guennadi Maximov C <g.maxc.fox@protonmail.com>
License-Expression: GPL-2.0-only
Project-URL: Download, https://github.com/DrKJeff16/vim-eof-comment/releases/latest
Project-URL: Funding, https://github.com/sponsors/DrKJeff16
Project-URL: Issues, https://github.com/DrKJeff16/vim-eof-comment/issues
Project-URL: Repository, https://github.com/DrKJeff16/vim-eof-comment
Keywords: eof comments,eof,files,preprocessing,text,vim modeline,vim,vim-eof
Classifier: Development Status :: 4 - Beta
Classifier: Environment :: Console
Classifier: Intended Audience :: Developers
Classifier: Intended Audience :: End Users/Desktop
Classifier: Operating System :: OS Independent
Classifier: Programming Language :: Python :: 3 :: Only
Classifier: Programming Language :: Python :: 3
Classifier: Programming Language :: Python :: 3.10
Classifier: Programming Language :: Python :: 3.11
Classifier: Programming Language :: Python :: 3.12
Classifier: Programming Language :: Python :: 3.13
Classifier: Programming Language :: Python :: 3.14
Classifier: Programming Language :: Python
Classifier: Topic :: Text Processing :: Filters
Classifier: Topic :: Utilities
Classifier: Typing :: Typed
Requires-Python: >=3.10
License-File: LICENSE
Requires-Dist: argcomplete
Requires-Dist: argparse
Requires-Dist: colorama
Dynamic: license-file
